olive/__init__.py
olive/__main__.py
olive/cache.py
olive/constants.py
olive/logging.py
olive/olive_config.json
olive/package_config.py
olive/resource_path.py
olive/assets/__init__.py
olive/assets/io_configs/__init__.py
olive/assets/io_configs/defaults.yaml
olive/assets/io_configs/diffusers.yaml
olive/assets/io_configs/tasks.yaml
olive/cli/__init__.py
olive/cli/api.py
olive/cli/auto_opt.py
olive/cli/base.py
olive/cli/benchmark.py
olive/cli/capture_onnx.py
olive/cli/configure_qualcomm_sdk.py
olive/cli/convert_adapters.py
olive/cli/diffusion_lora.py
olive/cli/extract_adapters.py
olive/cli/finetune.py
olive/cli/generate_adapter.py
olive/cli/generate_cost_model.py
olive/cli/launcher.py
olive/cli/optimize.py
olive/cli/quantize.py
olive/cli/run.py
olive/cli/run_pass.py
olive/cli/session_params_tuning.py
olive/cli/shared_cache.py
olive/common/__init__.py
olive/common/auto_config.py
olive/common/config_utils.py
olive/common/constants.py
olive/common/container_client_factory.py
olive/common/import_lib.py
olive/common/onnx_io.py
olive/common/ort_inference.py
olive/common/pydantic_v1.py
olive/common/user_module_loader.py
olive/common/utils.py
olive/common/hf/__init__.py
olive/common/hf/login.py
olive/common/hf/mappings.py
olive/common/hf/mlflow.py
olive/common/hf/model_io.py
olive/common/hf/peft.py
olive/common/hf/quant.py
olive/common/hf/utils.py
olive/common/hf/wrapper.py
olive/common/hf/io_config/__init__.py
olive/common/hf/io_config/input_generators.py
olive/common/hf/io_config/io_resolver.py
olive/common/hf/io_config/task_config.py
olive/common/hf/io_config/tasks.py
olive/common/quant/__init__.py
olive/common/quant/hf_utils.py
olive/common/quant/nn.py
olive/common/quant/utils.py
olive/data/__init__.py
olive/data/config.py
olive/data/constants.py
olive/data/registry.py
olive/data/template.py
olive/data/component/__init__.py
olive/data/component/dataloader.py
olive/data/component/dataset.py
olive/data/component/load_dataset.py
olive/data/component/post_process_data.py
olive_ai-0.11.0.dist-info/licenses/LICENSE
olive_ai-0.11.0.dist-info/licenses/NOTICE.txt
olive_ai-0.11.0.dist-info/METADATA
olive_ai-0.11.0.dist-info/WHEEL
olive_ai-0.11.0.dist-info/entry_points.txt
olive_ai-0.11.0.dist-info/top_level.txt
olive_ai-0.11.0.dist-info/RECORD
